corcondia/__init__.py
corcondia/corcondia.py
corcondia-0.1.1.dist-info/LICENSE
corcondia-0.1.1.dist-info/METADATA
corcondia-0.1.1.dist-info/WHEEL
corcondia-0.1.1.dist-info/top_level.txt
corcondia-0.1.1.dist-info/RECORD
