Metadata-Version: 2.1
Name: corcondia
Version: 0.1.1
Summary: An implementation of the CORCONDIA (Core Consistency Diagnostic) in Python.
Home-page: http://pypi.python.org/pypi/corcondia/
Author: William Shiao
Author-email: willshiao@gmail.com
License: MIT
Platform: UNKNOWN
License-File: LICENSE
Requires-Dist: tensorly
Requires-Dist: numpy
